{
  "version": "0.0.1",
  "catchAll": {},
  "startNode": "entry",
  "triggers": [],
  "description": "",
  "nodes": [
    {
      "id": "3f38a927f7",
      "name": "entry",
      "onEnter": [],
      "onReceive": null,
      "next": [
        {
          "condition": "true",
          "node": "women_rep"
        }
      ],
      "type": "standard"
    },
    {
      "id": "8081d44a13",
      "name": "women_rep",
      "next": [
        {
          "condition": "true",
          "node": ""
        }
      ],
      "onEnter": [],
      "onReceive": null,
      "type": "standard"
    }
  ]
}